det_executor/__init__.py
det_executor/api.py
det_executor/arches.py
det_executor/base.py
det_executor/image.py
det_executor/transformer.py
det_executor/v7.py
det_executor/v8.py
det_executor/models/__init__.py
det_executor/models/common.py
det_executor/models/experimental.py
det_executor/models/yolo.py
det_executor/utils/__init__.py
det_executor/utils/activations.py
det_executor/utils/add_nms.py
det_executor/utils/autoanchor.py
det_executor/utils/datasets.py
det_executor/utils/general.py
det_executor/utils/google_utils.py
det_executor/utils/load_utils.py
det_executor/utils/loss.py
det_executor/utils/metrics.py
det_executor/utils/torch_utils.py
det_executor/utils/aws/__init__.py
det_executor/utils/aws/resume.py
det_executor/utils/wandb_logging/__init__.py
det_executor/utils/wandb_logging/log_dataset.py
det_executor/utils/wandb_logging/wandb_utils.py
det_executor-0.0.9.dist-info/LICENSE
det_executor-0.0.9.dist-info/METADATA
det_executor-0.0.9.dist-info/WHEEL
det_executor-0.0.9.dist-info/top_level.txt
det_executor-0.0.9.dist-info/RECORD
