Metadata-Version: 2.1
Name: det-executor
Version: 0.0.9
Summary: Python package with latest versions of YOLO architecture for training and inference
Home-page: https://github.com/maxwolf8852/DetExecutor.git
Author: Maxim Volkovskiy
Author-email: maxwolf8852@gmail.com
Classifier: Programming Language :: Python :: 3.6
Classifier: License :: OSI Approved :: MIT License
Classifier: Operating System :: OS Independent
Requires-Python: >=3.6
License-File: LICENSE
Requires-Dist: pyyaml
Requires-Dist: opencv-python
Requires-Dist: torch
Requires-Dist: torchvision
Requires-Dist: requests
Requires-Dist: wget
Requires-Dist: tqdm
Requires-Dist: ultralytics
Requires-Dist: black
Requires-Dist: colorama
Requires-Dist: transformers
Requires-Dist: imageio[av]
